{
  "scraped_at": "2026-04-19T09:11:17.133604",
  "region": "北海道",
  "results": [
    {
      "company_id": "tempstaff",
      "company_name": "テンプスタッフ",
      "region": "北海道",
      "url": "https://www.tempstaff.co.jp/jbch/jobList/hokkaido/sd-51/sk-01#list",
      "count": 367,
      "avg_wage": 1400,
      "remote_ratio": 5.0,
      "error": null
    },
    {
      "company_id": "recruit_staffing",
      "company_name": "リクルートスタッフィング",
      "region": "北海道",
      "url": "https://www.r-staffing.co.jp/sol/op21/sd02/?kinmuArea=A0000&solDutyCd=A00&sort=1&pageNo=1&hyouziSuu=20&c=y&",
      "count": 104,
      "avg_wage": 1350,
      "remote_ratio": null,
      "error": null
    },
    {
      "company_id": "staff_service",
      "company_name": "スタッフサービス",
      "region": "北海道",
      "url": "https://www.staffservice.co.jp/hokkaido/office/haken/",
      "count": 895,
      "avg_wage": 1475,
      "remote_ratio": 25.0,
      "error": null
    },
    {
      "company_id": "adecco",
      "company_name": "アデコ",
      "region": "北海道",
      "url": "https://www.adecco.com/ja-jp/job/PO_JobListA?prefecture_city=%E5%8C%97%E6%B5%B7%E9%81%93&occupation=%E3%82%AA%E3%83%95%E3%82%A3%E3%82%B9%E3%83%AF%E3%83%BC%E3%82%AF%E3%83%BB%E4%BA%8B%E5%8B%99%E7%B3%BB",
      "count": 112,
      "avg_wage": 1400,
      "remote_ratio": 15.0,
      "error": null
    },
    {
      "company_id": "manpower",
      "company_name": "マンパワーグループ",
      "region": "北海道",
      "url": "https://www.manpowerjobnet.com/search/result/list/?JobCtgryClassCdList=201&PrfctrCdList=01",
      "count": 51,
      "avg_wage": null,
      "remote_ratio": null,
      "error": "Page.goto: Timeout 20000ms exceeded.\nCall log:\n  - navigating to \"https://www.manpowerjobnet.com/search/result/list/?Job"
    },
    {
      "company_id": "pasona",
      "company_name": "パソナ",
      "region": "北海道",
      "url": "https://www.pasona.co.jp/jobsearch/1001/result?place_wide_cd=1001&job_group_cd=133&job_group_cd=134&job_group_cd=135&job_group_cd=103&job_group_cd=104&job_group_cd=105&job_group_cd=106&job_group_cd=107&job_group_cd=115&job_group_cd=119&job_group_cd=121&salary_type=hour&income_ll=&income_ul=&dispatch_from__ymd=&place_pref_cd=01&keywords=",
      "count": 421,
      "avg_wage": 1450,
      "remote_ratio": null,
      "error": null
    }
  ]
}